_pytfmpval.cpython-38-darwin.so
tfm_utils/__init__.py
tfm_utils/pytfmpval.py
tfm_utils/tfmp.py
tfm_utils-0.0.2.dist-info/LICENSE.txt
tfm_utils-0.0.2.dist-info/METADATA
tfm_utils-0.0.2.dist-info/WHEEL
tfm_utils-0.0.2.dist-info/top_level.txt
tfm_utils-0.0.2.dist-info/RECORD
